chalkbox/__init__.py
chalkbox/components/__init__.py
chalkbox/components/alert.py
chalkbox/components/align.py
chalkbox/components/bar.py
chalkbox/components/code.py
chalkbox/components/columns.py
chalkbox/components/divider.py
chalkbox/components/dynamic_progress.py
chalkbox/components/json_view.py
chalkbox/components/kv.py
chalkbox/components/layout.py
chalkbox/components/markdown.py
chalkbox/components/padding.py
chalkbox/components/progress.py
chalkbox/components/progress_columns.py
chalkbox/components/prompt.py
chalkbox/components/section.py
chalkbox/components/spinner.py
chalkbox/components/status.py
chalkbox/components/status_card.py
chalkbox/components/stepper.py
chalkbox/components/table.py
chalkbox/components/tree.py
chalkbox/core/__init__.py
chalkbox/core/console.py
chalkbox/core/theme.py
chalkbox/live/__init__.py
chalkbox/live/dashboard.py
chalkbox/live/wrapper.py
chalkbox/logging/__init__.py
chalkbox/logging/bridge.py
chalkbox/py.typed
chalkbox-2.3.5.dist-info/LICENSE
chalkbox-2.3.5.dist-info/METADATA
chalkbox-2.3.5.dist-info/WHEEL
chalkbox-2.3.5.dist-info/RECORD
