Metadata-Version: 2.3
Name: chalkbox
Version: 2.3.5
Summary: A batteries-included CLI UI kit on top of Rich
License: MIT
Keywords: cli,ui,rich,terminal,console
Author: Robin Schulz
Author-email: bulletinmybeard@gmail.com
Requires-Python: >=3.12,<4.0
Classifier: Development Status :: 5 - Production/Stable
Classifier: Environment :: Console
Classifier: Intended Audience :: Developers
Classifier: License :: OSI Approved :: MIT License
Classifier: Operating System :: OS Independent
Classifier: Programming Language :: Python :: 3
Classifier: Programming Language :: Python :: 3.12
Classifier: Programming Language :: Python :: 3.13
Classifier: Topic :: Software Development :: Libraries :: Python Modules
Classifier: Topic :: Software Development :: User Interfaces
Classifier: Topic :: System :: Shells
Classifier: Topic :: Terminals
Classifier: Typing :: Typed
Requires-Dist: psutil (>=7.1.3,<8.0.0)
Requires-Dist: pydantic (>=2.12.4,<3.0.0)
Requires-Dist: pydantic-settings (>=2.12.0,<3.0.0)
Requires-Dist: rich (>=14.2.0,<15.0.0)
Requires-Dist: toml (>=0.10.2,<0.11.0)
Project-URL: Homepage, https://github.com/bulletinmybeard/chalkbox
Project-URL: Repository, https://github.com/bulletinmybeard/chalkbox
